MultiTool/Thread.py
MultiTool/__init__.py
MultiTool/time.py
example_pkg_Letsplayworria-0.0.1.dist-info/LICENSE
example_pkg_Letsplayworria-0.0.1.dist-info/METADATA
example_pkg_Letsplayworria-0.0.1.dist-info/WHEEL
example_pkg_Letsplayworria-0.0.1.dist-info/top_level.txt
example_pkg_Letsplayworria-0.0.1.dist-info/RECORD
