Metadata-Version: 2.1
Name: example-pkg-Letsplayworria
Version: 0.0.1
Summary: Help you to programming faster
Home-page: UNKNOWN
Author: Linus Pape
License: UNKNOWN
Platform: UNKNOWN
Classifier: Programming Language :: Python :: 3
Classifier: License :: OSI Approved :: MIT License
Classifier: Operating System :: OS Independent
Requires-Python: >=3.6
License-File: LICENSE
